<?xml version="1.0" encoding="UTF-8"?>
<gen_file>
 <group name="Root" depth_sorted_bin_value="1" depth_sorted_bin_state="0">
  <node_file name="FuselageNode" depth_sorted_bin_value="1" depth_sorted_bin_state="1" file="data/aircrafts/aw101/aw101_fuselage.osgt"/>
  <rotor name="MainRotor" depth_sorted_bin_value="1" convention="0" depth_sorted_bin_state="1" file_blade="data/aircrafts/aw101/aw101_rotor_blade.osgt" blades_count="5" direction="1" py="0.000000" ax="0.000000000000" az="0.000000000000" file_shaft="data/aircrafts/aw101/aw101_rotor_hub.osgt" pz="-3.570000" ay="-4.000000000000" px="0.000000" blades_offset="0.2"/>
  <pat name="TailRotorPAT" depth_sorted_bin_value="1" convention="0" depth_sorted_bin_state="0" py="-0.910000" ax="0.000000000000" az="0.000000000000" pz="-3.340000" ay="0.000000000000" px="-11.500000">
   <pat name="TailRotor" depth_sorted_bin_value="1" convention="0" depth_sorted_bin_state="0" py="0.000000" ax="0.000000000000" az="0.000000000000" pz="0.000000" ay="0.000000000000" px="0.000000">
    <node_file name="TailRotorNode" depth_sorted_bin_value="1" depth_sorted_bin_state="1" file="data/aircrafts/aw101/aw101_tail_rotor.osgt"/>
   </pat>
  </pat>
  <switch name="LandingGear" depth_sorted_bin_value="1" depth_sorted_bin_state="1" visible="1">
   <node_file name="LandingGearR" depth_sorted_bin_value="1" depth_sorted_bin_state="0" file="data/aircrafts/aw101/aw101_landing_gear_r.osgt"/>
   <group name="LandingGearE" depth_sorted_bin_value="1" depth_sorted_bin_state="0">
    <pat name="PAT_Wheel_L" depth_sorted_bin_value="1" convention="0" depth_sorted_bin_state="0" py="-1.780000" ax="0.000000000000" az="0.000000000000" pz="0.200000" ay="0.000000000000" px="-1.980000">
     <pat name="LandingGear1" depth_sorted_bin_value="1" convention="0" depth_sorted_bin_state="0" py="0.000000" ax="0.000000000000" az="0.000000000000" pz="0.000000" ay="0.000000000000" px="0.000000">
      <node_file name="FileNode" depth_sorted_bin_value="1" depth_sorted_bin_state="0" file="data/aircrafts/aw101/aw101_landing_gear_wheel_l.osgt"/>
     </pat>
    </pat>
    <pat name="PAT_Wheel_R" depth_sorted_bin_value="1" convention="0" depth_sorted_bin_state="0" py="1.780000" ax="0.000000000000" az="0.000000000000" pz="0.200000" ay="0.000000000000" px="-1.980000">
     <pat name="LandingGear2" depth_sorted_bin_value="1" convention="0" depth_sorted_bin_state="0" py="0.000000" ax="0.000000000000" az="0.000000000000" pz="0.000000" ay="0.000000000000" px="0.000000">
      <node_file name="FileNode" depth_sorted_bin_value="1" depth_sorted_bin_state="0" file="data/aircrafts/aw101/aw101_landing_gear_wheel_r.osgt"/>
     </pat>
    </pat>
    <pat name="PAT_Wheel_N" depth_sorted_bin_value="1" convention="0" depth_sorted_bin_state="0" py="0.000000" ax="0.000000000000" az="0.000000000000" pz="0.400000" ay="0.000000000000" px="5.050000">
     <pat name="LandingGear3" depth_sorted_bin_value="1" convention="0" depth_sorted_bin_state="0" py="0.000000" ax="0.000000000000" az="0.000000000000" pz="0.000000" ay="0.000000000000" px="0.000000">
      <node_file name="FileNode" depth_sorted_bin_value="1" depth_sorted_bin_state="0" file="data/aircrafts/aw101/aw101_landing_gear_wheel_n.osgt"/>
     </pat>
    </pat>
   </group>
  </switch>
 </group>
</gen_file>
